bunch/__init__.py
bunch/bunch.py
bunch/immutable_bunch.py
python_bunch-0.1.7.dist-info/licenses/LICENSE
python_bunch-0.1.7.dist-info/METADATA
python_bunch-0.1.7.dist-info/WHEEL
python_bunch-0.1.7.dist-info/top_level.txt
python_bunch-0.1.7.dist-info/RECORD
