Metadata-Version: 2.4
Name: python-bunch
Version: 0.1.7
Summary: A lightweight Python class that behaves like a dict but supports attribute-style access.
Author-email: Omer Menashe <unspecified@mail.com>
License: MIT
Project-URL: Source, https://github.com/iamomerm/python-bunch
Keywords: python-bunch,bunch,dict,attribute-access,json,utility
Classifier: Programming Language :: Python :: 3
Classifier: License :: OSI Approved :: MIT License
Classifier: Operating System :: OS Independent
Requires-Python: >=3.7
License-File: LICENSE
Dynamic: license-file
